{
  "tracks": [
    {
      "id": "bg_music",
      "title": "Tema Alesia",
      "durationSec": 90,
      "bpm": 96,
      "markers": [
        {
          "label": "Intro",
          "timeSec": 0
        },
        {
          "label": "A",
          "timeSec": 16
        },
        {
          "label": "B",
          "timeSec": 40
        },
        {
          "label": "C",
          "timeSec": 64
        }
      ]
    },
    {
      "id": "song_1",
      "title": "Valsul Stelelor",
      "durationSec": 120,
      "bpm": 120,
      "markers": [
        {
          "label": "Intro",
          "timeSec": 0
        },
        {
          "label": "Refren",
          "timeSec": 45
        },
        {
          "label": "Punte",
          "timeSec": 75
        }
      ]
    },
    {
      "id": "song_2",
      "title": "Dansul Pădurii",
      "durationSec": 105,
      "bpm": 110,
      "markers": [
        {
          "label": "Intro",
          "timeSec": 0
        },
        {
          "label": "A",
          "timeSec": 30
        },
        {
          "label": "B",
          "timeSec": 60
        },
        {
          "label": "C",
          "timeSec": 90
        }
      ]
    }
  ]
}